.gitignore
CHANGES.txt
CONTRIBUTORS.txt
COPYRIGHT.txt
LICENSE.txt
README.txt
setup.cfg
setup.py
tox.ini
docs/.gitignore
docs/Makefile
docs/conf.py
docs/index.rst
docs/_static/exclaim.png
docs/_static/exclaim_color.png
docs/_static/info.png
docs/_static/info_color.png
docs/_static/onebit_36.png
docs/_static/onebit_38.png
docs/_static/pyramid.png
docs/_static/pyramid_epub.css
pyramid_chameleon_genshi/__init__.py
pyramid_chameleon_genshi/configure.zcml
pyramid_chameleon_genshi.egg-info/PKG-INFO
pyramid_chameleon_genshi.egg-info/SOURCES.txt
pyramid_chameleon_genshi.egg-info/dependency_links.txt
pyramid_chameleon_genshi.egg-info/entry_points.txt
pyramid_chameleon_genshi.egg-info/not-zip-safe
pyramid_chameleon_genshi.egg-info/requires.txt
pyramid_chameleon_genshi.egg-info/top_level.txt
pyramid_chameleon_genshi/tests/__init__.py
pyramid_chameleon_genshi/tests/test_chameleon_genshi.py
pyramid_chameleon_genshi/tests/fixtures/.gitignore
pyramid_chameleon_genshi/tests/fixtures/minimal.genshi