Metadata-Version: 1.0
Name: pyramid-chameleon-genshi
Version: 0.6
Summary: chameleon.genshi template bindings for the Pyramid web framework
Home-page: http://docs.pylonshq.com
Author: Chris McDonough, Agendaless Consulting
Author-email: pylons-devel@googlegroups.com
License: BSD-derived (http://www.repoze.org/LICENSE.txt)
Keywords: bfg pyramid pylons genshi chameleon templates
Platform: UNKNOWN
Classifier: Intended Audience :: Developers
Classifier: Programming Language :: Python
Classifier: Topic :: Internet :: WWW/HTTP :: Dynamic Content
